openapi_schema_validator/__init__.py
openapi_schema_validator/_format.py
openapi_schema_validator/_keywords.py
openapi_schema_validator/_types.py
openapi_schema_validator/py.typed
openapi_schema_validator/shortcuts.py
openapi_schema_validator/validators.py
openapi_schema_validator-0.6.1.dist-info/LICENSE
openapi_schema_validator-0.6.1.dist-info/METADATA
openapi_schema_validator-0.6.1.dist-info/WHEEL
openapi_schema_validator-0.6.1.dist-info/RECORD
