Metadata-Version: 2.1
Name: openapi-schema-validator
Version: 0.6.1
Summary: OpenAPI schema validation for Python
Home-page: https://github.com/python-openapi/openapi-schema-validator
License: BSD-3-Clause
Keywords: openapi,swagger,schema
Author: Artur Maciag
Author-email: maciag.artur@gmail.com
Requires-Python: >=3.8.0,<4.0.0
Classifier: Development Status :: 4 - Beta
Classifier: Intended Audience :: Developers
Classifier: License :: OSI Approved :: BSD License
Classifier: Operating System :: OS Independent
Classifier: Programming Language :: Python :: 3
Classifier: Programming Language :: Python :: 3.8
Classifier: Programming Language :: Python :: 3.9
Classifier: Programming Language :: Python :: 3.10
Classifier: Programming Language :: Python :: 3.11
Classifier: Topic :: Software Development :: Libraries
Classifier: Topic :: Software Development :: Libraries :: Python Modules
Provides-Extra: docs
Requires-Dist: jsonschema (>=4.19.1,<5.0.0)
Requires-Dist: jsonschema-specifications (>=2023.5.2,<2024.0.0)
Requires-Dist: rfc3339-validator
Project-URL: Repository, https://github.com/python-openapi/openapi-schema-validator
